aerie_cli/__init__.py
aerie_cli/__main__.py
aerie_cli/__version__.py
aerie_cli/aerie_client.py
aerie_cli/aerie_host.py
aerie_cli/app.py
aerie_cli/commands/command_context.py
aerie_cli/commands/configurations.py
aerie_cli/commands/constraints.py
aerie_cli/commands/expansion.py
aerie_cli/commands/metadata.py
aerie_cli/commands/models.py
aerie_cli/commands/plans.py
aerie_cli/commands/scheduling.py
aerie_cli/persistent.py
aerie_cli/py.typed
aerie_cli/schemas/__init__.py
aerie_cli/schemas/api.py
aerie_cli/schemas/client.py
aerie_cli/utils/__init__.py
aerie_cli/utils/configurations.py
aerie_cli/utils/prompts.py
aerie_cli/utils/serialization.py
aerie_cli/utils/sessions.py
aerie_cli-2.10.2.dist-info/METADATA
aerie_cli-2.10.2.dist-info/WHEEL
aerie_cli-2.10.2.dist-info/entry_points.txt
aerie_cli-2.10.2.dist-info/licenses/LICENSE
aerie_cli-2.10.2.dist-info/RECORD
