Metadata-Version: 2.4
Name: aerie-cli
Version: 2.10.2
Summary: A CLI application and Python API for interacting with Aerie.
License: MIT
License-File: LICENSE
Requires-Python: >=3.6.8
Classifier: License :: OSI Approved :: MIT License
Classifier: Programming Language :: Python :: 3
Classifier: Programming Language :: Python :: 3.7
Classifier: Programming Language :: Python :: 3.8
Classifier: Programming Language :: Python :: 3.9
Classifier: Programming Language :: Python :: 3.10
Classifier: Programming Language :: Python :: 3.11
Classifier: Programming Language :: Python :: 3.12
Classifier: Programming Language :: Python :: 3.13
Classifier: Programming Language :: Python :: 3.14
Requires-Dist: appdirs (>=1.4.4,<2.0.0)
Requires-Dist: arrow (>=1.2.2)
Requires-Dist: attrs (>=22.2.0,<23.0.0)
Requires-Dist: click (>=8.0.1)
Requires-Dist: importlib-metadata (>=4.8.2,<5.0.0) ; python_version < "3.8"
Requires-Dist: numpy (>=1.19.5,<2.0.0) ; python_version < "3.7"
Requires-Dist: pandas (>=1.1.5)
Requires-Dist: requests (>=2.27.1,<3.0.0)
Requires-Dist: rich (>=12.6.0,<13.0.0)
Requires-Dist: typer (>=0.10.0)
Project-URL: Repository, https://github.com/NASA-AMMOS/aerie-cli
